README.md
setup.cfg
setup.py
delayer/__init__.py
delayer/catcher.py
delayer/delayers.py
delayer.egg-info/PKG-INFO
delayer.egg-info/SOURCES.txt
delayer.egg-info/dependency_links.txt
delayer.egg-info/not-zip-safe
delayer.egg-info/top_level.txt