Metadata-Version: 1.0
Name: delayer
Version: 0.1
Summary: Delay wrappers
Home-page: UNKNOWN
Author: UNKNOWN
Author-email: UNKNOWN
License: UNKNOWN
Platform: UNKNOWN
